design.sv
module sync_fifo (
     // write  interface
     clk_i, rst_i, wdata_i, full_o, wr_en_i, wr_error_o,
     // read interface
     rdata_o, empty_o, rd_en_i, rd_error_o
);
parameter DEPTH=16, WIDTH=8, PTR_WIDTH=4;
//wr_ptr is internal to the design
//declare all inputs and output
input clk_i,rst_i,wr_en_i,rd_en_i;
input [WIDTH-1 : 0] wdata_i;
output reg [WIDTH-1 : 0] rdata_o;
output reg full_o, empty_o, wr_error_o, rd_error_o;

//wr_ptr, rd_ptr, toggle flags(scalar)
reg [PTR_WIDTH-1:0] wr_ptr, rd_ptr;
reg wr_toggle_f, rd_toggle_f; 
//declare the memory
reg [WIDTH-1 : 0] mem [DEPTH-1:0];
integer i;

 /*processes in fifo
  write,read => do they happen on same clock or different clock -> Same clock
 both can be coded in to same always block*/
always @(posedge clk_i) begin
if (rst_i==1) begin
  // all reg variables assign to reset values
   rdata_o = 0;
   full_o = 0;
   empty_o = 1;
   wr_error_o = 0;
   rd_error_o = 0;
   wr_ptr = 0;
   rd_ptr = 0;
   wr_toggle_f = 0;
   rd_toggle_f = 0;
   //mem = 0; //wrong
   for (i=0; i< DEPTH; i=i+1) begin
      mem[i] = 1;
  end
end
else begin //rst_i not applied
//write can happen
if (wr_en_i == 1) begin
if (full_o == 1 ) begin
  wr_error_o = 1;
end
else begin
//store data into memeory
  mem [wr_ptr] = wdata_i;
  wr_error_o = 0;
//increment the wr_ptr
if (wr_ptr == DEPTH-1) wr_toggle_f = ~wr_toggle_f;
  wr_ptr = wr_ptr + 1;  //DEPTH-1 -> DEPTH(16)=>0
        end
    end
//read can happen 
if (rd_en_i == 1 ) begin
   if (empty_o ==1) begin
       rd_error_o = i;
end
else begin
  rdata_o = mem [rd_ptr];
  rd_error_o = 0;
if (rd_ptr == DEPTH-1) rd_toggle_f = ~rd_toggle_f;
//increment the rd_ptr
rd_ptr = rd_ptr+1;
         end
      end
  end
end

//logic for full and empty generation
//sequential logic or combinational logic => Combinational logic
always @(*) begin
  //wr_ptr, rd_ptr, wr_toggle_f, rd_toggle_f
empty_o = 0;
full_o = 0;
if (wr_ptr == rd_ptr) begin
   if (wr_toggle_f == rd_toggle_f) empty_o = 1;
   if (wr_toggle_f != rd_toggle_f) full_o = 1;
   end
end
endmodule

testbench.sv

module sync_fifotb;
parameter DEPTH=16, WIDTH=8, PTR_WIDTH=4;
reg clk_i,rst_i,wr_en_i,rd_en_i;
reg [WIDTH-1 : 0] wdata_i;
wire [WIDTH-1 : 0] rdata_o;
wire full_o, empty_o, wr_error_o, rd_error_o;
integer i;

sync_fifo dut (
      clk_i, rst_i, wdata_i, full_o, wr_en_i, wr_error_o,
      rdata_o, empty_o, rd_en_i, rd_error_o
);

//clock generation
initial begin
clk_i = 0;
$dumpfile ("fifoh.vcd");
$dumpvars (0,sync_fifotb); 
$monitor ($time,"rst_i = %b , wr_en_i= %b , rd_en_i = %b,wdata_i = %b,rdata_o = %b ,full_o = %b, empty_o = %b, wr_error_o = %b, rd_error_o = %b ",rst_i,wr_en_i,rd_en_i,wdata_i,rdata_o,full_o, empty_o, wr_error_o, rd_error_o) ;
forever #5 clk_i = ~clk_i;
//don't code anything after forever in any language
end

//reset apply, release
initial begin
rst_i = 1;   //apply
@(posedge clk_i);  //holding
rst_i = 0;  //releasing
//now design in a state where we can apply the inputs 
//apply stimulus write to the FIFO and read from the FIFO
for (i=0; i< DEPTH; i=i+1) begin
@(posedge clk_i);
wr_en_i = 1;
wdata_i = $random;
end
@(posedge clk_i);
wr_en_i = 0;
wdata_i = 0;
//read from FIFO
for (i=0; i< DEPTH; i=i+1) begin
@(posedge clk_i);
rd_en_i = 1;
end
@(posedge clk_i);
rd_en_i = 0;
$finish;
end
endmodule

fifoh.vcd
$date
Tue Aug 22 12:32:57 2023
$end
$version
Riviera-PRO Version 2022.04.117.8517
$end
$timescale
1 ns
$end

$scope module sync_fifotb $end
$var wire 8 ! rdata_o [7:0] $end
$var wire 1 " full_o $end
$var wire 1 # empty_o $end
$var wire 1 $ wr_error_o $end
$var wire 1 % rd_error_o $end
$var reg 1 & clk_i $end
$var reg 1 ' rst_i $end
$var reg 1 ( wr_en_i $end
$var reg 1 ) rd_en_i $end
$var reg 8 * wdata_i [7:0] $end
$var integer 32 + i $end
$var parameter 32 , DEPTH [31:0] $end
$var parameter 32 - WIDTH [31:0] $end
$var parameter 32 . PTR_WIDTH [31:0] $end

$scope module dut $end
$var wire 1 / clk_i $end
$var wire 1 0 rst_i $end
$var wire 8 1 wdata_i [7:0] $end
$var wire 1 2 wr_en_i $end
$var wire 1 3 rd_en_i $end
$var reg 1 4 full_o $end
$var reg 1 5 wr_error_o $end
$var reg 8 6 rdata_o [7:0] $end
$var reg 1 7 empty_o $end
$var reg 1 8 rd_error_o $end
$var reg 4 9 wr_ptr [3:0] $end
$var reg 4 : rd_ptr [3:0] $end
$var reg 1 ; wr_toggle_f $end
$var reg 1 < rd_toggle_f $end
$var integer 32 = i $end
$var parameter 32 > DEPTH [31:0] $end
$var parameter 32 ? WIDTH [31:0] $end
$var parameter 32 @ PTR_WIDTH [31:0] $end
$upscope $end

$upscope $end

$enddefinitions $end
$dumpvars
bx !
x"
x#
x$
x%
0&
1'
x(
x)
bx *
bx +
b10000 ,
b1000 -
b100 .
0/
10
bx 1
x2
x3
x4
x5
bx 6
x7
x8
bx 9
bx :
x;
x<
bx =
b10000 >
b1000 ?
b100 @
$end
#5
1&
1/
0'
b0 +
b0 6
04
17
05
08
b0 9
b0 :
0;
0<
b10000 =
0%
0$
1#
0"
b0 !
00
17
#10
0&
0/
#15
1&
1/
1(
b100100 *
b1 +
b100100 1
12
#20
0&
0/
#25
1&
1/
b10000001 *
b10 +
b1 9
b10000001 1
07
0#
#30
0&
0/
#35
1&
1/
b1001 *
b11 +
b10 9
b1001 1
#40
0&
0/
#45
1&
1/
b1100011 *
b100 +
b11 9
b1100011 1
#50
0&
0/
#55
1&
1/
b1101 *
b101 +
b100 9
b1101 1
#60
0&
0/
#65
1&
1/
b10001101 *
b110 +
b101 9
b10001101 1
#70
0&
0/
#75
1&
1/
b1100101 *
b111 +
b110 9
b1100101 1
#80
0&
0/
#85
1&
1/
b10010 *
b1000 +
b111 9
b10010 1
#90
0&
0/
#95
1&
1/
b1 *
b1001 +
b1000 9
b1 1
#100
0&
0/
#105
1&
1/
b1101 *
b1010 +
b1001 9
b1101 1
#110
0&
0/
#115
1&
1/
b1110110 *
b1011 +
b1010 9
b1110110 1
#120
0&
0/
#125
1&
1/
b111101 *
b1100 +
b1011 9
b111101 1
#130
0&
0/
#135
1&
1/
b11101101 *
b1101 +
b1100 9
b11101101 1
#140
0&
0/
#145
1&
1/
b10001100 *
b1110 +
b1101 9
b10001100 1
#150
0&
0/
#155
1&
1/
b11111001 *
b1111 +
b1110 9
b11111001 1
#160
0&
0/
#165
1&
1/
b11000110 *
b10000 +
b1111 9
b11000110 1
#170
0&
0/
#175
1&
1/
0(
b0 *
b0 +
1;
b0 9
b0 1
02
14
1"
#180
0&
0/
#185
1&
1/
1)
b1 +
13
#190
0&
0/
#195
1&
1/
b10 +
b100100 6
b1 :
b100100 !
04
0"
#200
0&
0/
#205
1&
1/
b11 +
b10000001 6
b10 :
b10000001 !
#210
0&
0/
#215
1&
1/
b100 +
b1001 6
b11 :
b1001 !
#220
0&
0/
#225
1&
1/
b101 +
b1100011 6
b100 :
b1100011 !
#230
0&
0/
#235
1&
1/
b110 +
b1101 6
b101 :
b1101 !
#240
0&
0/
#245
1&
1/
b111 +
b10001101 6
b110 :
b10001101 !
#250
0&
0/
#255
1&
1/
b1000 +
b1100101 6
b111 :
b1100101 !
#260
0&
0/
#265
1&
1/
b1001 +
b10010 6
b1000 :
b10010 !
#270
0&
0/
#275
1&
1/
b1010 +
b1 6
b1001 :
b1 !
#280
0&
0/
#285
1&
1/
b1011 +
b1101 6
b1010 :
b1101 !
#290
0&
0/
#295
1&
1/
b1100 +
b1110110 6
b1011 :
b1110110 !
#300
0&
0/
#305
1&
1/
b1101 +
b111101 6
b1100 :
b111101 !
#310
0&
0/
#315
1&
1/
b1110 +
b11101101 6
b1101 :
b11101101 !
#320
0&
0/
#325
1&
1/
b1111 +
b10001100 6
b1110 :
b10001100 !
#330
0&
0/
#335
1&
1/
b10000 +
b11111001 6
b1111 :
b11111001 !
#340
0&
0/
#345
1&
1/
0)
